pygoic/__init__.py
pygoic/channel.py
pygoic/context.py
pygoic/executor.py
pygoic/linked.py
pygoic/sync.py
pygoic/time.py
pygoic-0.1.2.dist-info/LICENSE
pygoic-0.1.2.dist-info/METADATA
pygoic-0.1.2.dist-info/WHEEL
pygoic-0.1.2.dist-info/RECORD
