Metadata-Version: 2.1
Name: pygoic
Version: 0.1.2
Summary: A Go-like asynchronous concurrency library.
License: MIT
Author: Xiaodong Yang
Author-email: yxdong.cc@outlook.com
Requires-Python: >=3.8,<4.0
Classifier: License :: OSI Approved :: MIT License
Classifier: Programming Language :: Python :: 3
Classifier: Programming Language :: Python :: 3.8
Classifier: Programming Language :: Python :: 3.9
Classifier: Programming Language :: Python :: 3.10
Classifier: Programming Language :: Python :: 3.11
